toolbox_sdk/__init__.py
toolbox_sdk/client.py
toolbox_sdk/exceptions.py
toolbox_sdk/mime_types.py
toolbox_sdk/types.py
toolbox_sdk/version.py
toolbox_sdk-0.1.0b3.dist-info/METADATA
toolbox_sdk-0.1.0b3.dist-info/WHEEL
toolbox_sdk-0.1.0b3.dist-info/licenses/LICENSE
toolbox_sdk-0.1.0b3.dist-info/RECORD
