Metadata-Version: 2.4
Name: toolbox-sdk
Version: 0.1.0b3
Summary: Official Python SDK for NextGIS Toolbox providing convenient access to geographical data processing tools
Project-URL: Homepage, https://github.com/nextgis/toolbox_sdk
Project-URL: Repository, https://github.com/nextgis/toolbox_sdk.git
Project-URL: Issues, https://github.com/nextgis/toolbox_sdk/issues
Author-email: NextGIS <info@nextgis.com>
License-File: LICENSE
Keywords: geography,geospatial,gis,mapping,nextgis,spatial,toolbox
Classifier: Development Status :: 4 - Beta
Classifier: Intended Audience :: Developers
Classifier: Intended Audience :: Science/Research
Classifier: License :: OSI Approved :: MIT License
Classifier: Operating System :: OS Independent
Classifier: Programming Language :: Python :: 3
Classifier: Programming Language :: Python :: 3.8
Classifier: Programming Language :: Python :: 3.9
Classifier: Programming Language :: Python :: 3.10
Classifier: Programming Language :: Python :: 3.11
Classifier: Topic :: Scientific/Engineering :: GIS
Classifier: Topic :: Software Development :: Libraries :: Python Modules
Requires-Python: >=3.8
Requires-Dist: requests>=2.28.0
Provides-Extra: dev
Requires-Dist: pytest>=8.3.4; extra == 'dev'
Requires-Dist: python-dotenv>=1.0.1; extra == 'dev'
Requires-Dist: responses>=0.25.3; extra == 'dev'
